PyPlanPro/__init__.py
PyPlanPro/models/__init__.py
PyPlanPro/models/resource.py
PyPlanPro/models/resource_group.py
PyPlanPro/models/task.py
PyPlanPro/scheduler/__init__.py
PyPlanPro/scheduler/core.py
PyPlanPro/scheduler/heuristic_solver.py
PyPlanPro/scheduler/optimizer.py
PyPlanPro/scheduler/scheduler_result.py
PyPlanPro/scheduler/visualizations.py
tests/__init__.py
tests/scheduler/__init__.py
tests/scheduler/test_heuristic_solver.py
tests/scheduler/test_scheduler.py
pyplanpro-0.0.9.dist-info/LICENSE
pyplanpro-0.0.9.dist-info/METADATA
pyplanpro-0.0.9.dist-info/WHEEL
pyplanpro-0.0.9.dist-info/top_level.txt
pyplanpro-0.0.9.dist-info/RECORD
