Metadata-Version: 2.1
Name: pyplanpro
Version: 0.0.9
Summary: Task scheduler for python
Home-page: https://github.com/Oestergaard-A-S/PyPlanPro
Author: Jacob Østergaard Nielsen
Author-email: jaoe@oestergaard-as.dk
Classifier: Development Status :: 3 - Alpha
Classifier: License :: OSI Approved :: GNU General Public License v3 (GPLv3)
Classifier: Programming Language :: Python :: 3
License-File: LICENSE
Requires-Dist: ortools
Requires-Dist: intervaltree
Requires-Dist: networkx
Requires-Dist: pandas
